{
  "chunk_id": "ahc-model__codebook-ahc_pdf__2ecadb1aec__p21__chunk_0",
  "source_document": "data/raw/assets/pdf/2ecadb1aec0f9d6e0f07a7cc628ccf35b46ec6c5.pdf",
  "page": 21,
  "text": "Chronic Conditions Warehouse Virtual Research Data Center \nAHC Model Data File Codebook │ December 2024 │ V 1.0 20 \n\nBENE_RACE_ETHNCTY_CD \n\nLABEL: Beneficiary Race and Ethnicity \n\nDESCRIPTION: Beneficiary race and ethnicity code. \n\nLONG NAME: BENE_RACE_ETHNCTY_CD \n\nTYPE: CHAR \n\nLENGTH: 1 \n\nSOURCE: AHC data system \nCCW \n\nVALUES: 1 = American Indian or Alaska Native \n2 = Asian or Hawaiian or Other Pacific Islander \n3 = Black or African American \n4 = Hispanic or Latino \n5 = White \n6 = Other Race",
  "dataset": "ahc-model",
  "url": "https://www2.ccwdata.org/documents/10280/19022436/codebook-ahc.pdf"
}