{
  "chunk_id": "ahc-model__codebook-ahc_pdf__2ecadb1aec__p32__chunk_0",
  "source_document": "data/raw/assets/pdf/2ecadb1aec0f9d6e0f07a7cc628ccf35b46ec6c5.pdf",
  "page": 32,
  "text": "Chronic Conditions Warehouse Virtual Research Data Center \nAHC Model Data File Codebook │ December 2024 │ V 1.0 31 \n\nNE_NVGTR_SUCSFL_CNTCT_NUM \n\nLABEL: Number of navigator successful contacts with beneficiary \n\nDESCRIPTION: Navigator event (NE) summarizing the total number of navigator successful contacts with beneficiary. \n\nLONG NAME: NE_NVGTR_SUCSFL_CNTCT_NUM \n\nTYPE: NUM \n\nLENGTH: 2 \n\nSOURCE: AHC data system (derived) \n\nVALUES: 0–57 \nMissing \n\nCOMMENT: CMS did not require bridge organizations",
  "dataset": "ahc-model",
  "url": "https://www2.ccwdata.org/documents/10280/19022436/codebook-ahc.pdf"
}