{
  "chunk_id": "ahc-model__chunk_5",
  "source_document": "data/raw/html/dataset_page/1c35797b5493f4e27d3fcca1632661f8063b4618.html",
  "page": null,
  "text": "(e.g. food, housing, safety, transportation, utilities) are reported. Some beneficiaries also have supplemental indicators related to disabilities, education, employment, family and community support, mental health, physical activity, and substance use. For screened items where a need is identified, the file contains information about services offered and their outcomes.\nWhat does this file include? (variable highlights)\nPerson level identifiers (i.e., BENE_ID, MSIS_ID) that researchers can use",
  "dataset": "ahc-model",
  "url": "https://resdac.org/cms-data/files/ahc-model"
}