{
  "chunk_id": "cahps__ffs-cahps-datadictionary-2025-ccw_pdf__ca6eb08dee__p57__chunk_0",
  "source_document": "data/raw/assets/pdf/ca6eb08deec69a2ca0c053e0e47dab882908b143.pdf",
  "page": 57,
  "text": "A. Crosswalk: 2007 to 2025 - Original Medicare Survey 57 \n\nVariable Reverse 2007 \nYear 1 \n\nrace_white Q59A \nrace_black Q59B \nrace_asian Q59C \nrace_pacific Q59D \nrace_natamer Q59E \nproxy Q60 \nproxy_read Q61A \nproxy_writ Q61B \nproxy_answ Q61C \nproxy_tran Q61D \nproxy_othr Q61E \nproxy_othr_txt Q61_O \nliving_arr Q62 \nliving_arr_txt Q62_O \nliving_alone \nliving_numinhh \nlim_bathing Q63A \nlim_dressing Q63B \nlim_eating Q63C \nlim_chairs Q63D \nlim_walking Q63E \nlim_toilet Q63F \nweb_at_home \nrecontact Q64",
  "dataset": "cahps",
  "url": "https://resdac.org/sites/datadocumentation.resdac.org/files/2026-05/FFS_CAHPS_DataDictionary_2025_CCW.pdf"
}