{
  "chunk_id": "cahps__ma-pdp-cahps-datadictionary-2025-ccw_pdf__d2602cbe44__p8__chunk_0",
  "source_document": "data/raw/assets/pdf/d2602cbe44c673c77cf8472b3ff5f084d5a5c3aa.pdf",
  "page": 8,
  "text": "A. 2025 MCAHPS Analytic Data Contents\n\nname LABEL FORMAT\n\ncs_csgetinfo RECODE : Last 6 mths, how often health plan customer service give info OFA\ncs_csrespect RECODE : Last 6 mths, how often health plan customer service treat w/respect and courtesy OFA\npd_ﬁllrx RECODE : Last 6 mths, dr/pharmacy/pdp contact: make sure ﬁll or reﬁll rx YNA\npd_takemeds RECODE : Last 6 mths, dr/pharmacy/pdp contact: make sure take meds as directed YNA\npd_ezrxmeds RECODE : Last 6 mths, easy to use pdp to get rx meds",
  "dataset": "cahps",
  "url": "https://resdac.org/sites/datadocumentation.resdac.org/files/2026-05/MA_PDP_CAHPS_DataDictionary_2025_CCW.pdf"
}