{
  "chunk_id": "cahps__ma-pdp-cahps-datadictionary-2025-ccw_pdf__d2602cbe44__p35__chunk_6",
  "source_document": "data/raw/assets/pdf/d2602cbe44c673c77cf8472b3ff5f084d5a5c3aa.pdf",
  "page": 35,
  "text": "did you have an illness, injury, or condition that needed care right away?\nFFS\nMA-PD\nca_illasaw MA-Only Q04 In the last 6 months, when you needed care right away, how often did you get care as soon as you needed?\nFFS\nMA-PD\nca_routine MA-Only Q05 In the last 6 months, did you make any in-person, phone, or video appointments for a check-up or routine care?\nFFS\nMA-PD\nca_rtnasaw MA-Only Q06 In the last 6 months, how often did you get an appointment for a check-up or routine care as soon as you",
  "dataset": "cahps",
  "url": "https://resdac.org/sites/datadocumentation.resdac.org/files/2026-05/MA_PDP_CAHPS_DataDictionary_2025_CCW.pdf"
}