{
  "chunk_id": "cahps__ma-pdp-cahps-datadictionary-2025-ccw_pdf__d2602cbe44__p94__chunk_0",
  "source_document": "data/raw/assets/pdf/d2602cbe44c673c77cf8472b3ff5f084d5a5c3aa.pdf",
  "page": 94,
  "text": "B. Composites: 2007 to 2025 - MA-Only Survey 94\n\nComposite Item 2016 2015 2014 2013 2012 2011 2010 2009 2008\nYear 10 Year 9 Year 8 Year 7 Year 6 Year 5 Year 4 Year 3 Year 2\n\npdp_getinfo pd_getcovinf —– —– —– —– —– —– —– —– —–\npd_getcostinf —– —– —– —– —– —– —– —– —–\npd_infocov\npd_csgetinfo —– —– —– —– —– —– —– —– —–\npd_csrespect —– —– —– —– —– —– —– —– —–\n\npdp_getdrug pd_ezrxmeds —– —– —– —– —– —– —– —– —–\npd_ezrxpharmˆ —– —– —– —– —– —– —– —– —–\npd_ezrxmailˆ —– —– —– —– —– —– —– —–",
  "dataset": "cahps",
  "url": "https://resdac.org/sites/datadocumentation.resdac.org/files/2026-05/MA_PDP_CAHPS_DataDictionary_2025_CCW.pdf"
}