{
  "chunk_id": "hedis-rif__record-layout-hedis_xlsx__12d0d2cc9d__s1__chunk_121",
  "source_document": "data/raw/assets/xlsx/12d0d2cc9dacbb09dd6e9287b10bee19e1a205f6.xlsx",
  "page": 1,
  "text": "Transitions of Care (TRC) Nmrtr: Receipt of Discharge Info (RDI) Count 65+ Yrs NUM 3 — 251 299 287 285\nTRC_DNMTR_PEID_AGE_GE65_CNT Transitns of Care (TRC) Dnmtr: Patient Engmnt aftr IP Dschrg (PEID) Cnt 65+ Yrs NUM 3 — 252 300 288 286\nTRC_NMRTR_PEID_AGE_GE65_CNT Transitions of Care (TRC) Nmrtr: Pt Engmnt aftr IP Dschrg (PEID) Count 65+ Yrs NUM 3 — 253 301 289 287\nTRC_DNMTR_MRPD_AGE_GE65_CNT Transitns of Care (TRC) Medctn Rec Post-Dschrg (MRPD) Dnmtr: Dschrg Cnt 65+ Yrs NUM 3 — 254 302 290",
  "dataset": "hedis-rif",
  "url": "https://www2.ccwdata.org/documents/10280/19022436/record-layout-hedis.xlsx"
}