{
  "chunk_id": "hha-ffs__bp102c07_pdf__551d41d9a2__p94__chunk_4",
  "source_document": "data/raw/assets/pdf/551d41d9a2e0df08a63c3215d57d55efb3708dd1.pdf",
  "page": 94,
  "text": "affiliated with a medical school must all be qualified providers of services. However, \nthere are special provisions for the use of the facilities of rehabilitation centers. The cost \nof transporting an individual to a facility cannot be reimbursed as home health services. \n\n50.7 - Part-Time or Intermittent Home Health Aide and Skilled Nursing \nServices \n(Rev. 1, 10-01-03) \nA3-3119.7, HHA-206.7, A3-3119.7A, HHA-206.7A, A3-3119.7.B, HHA-206.7.B \n\nWhere a patient is eligible for coverage of home",
  "dataset": "hha-ffs",
  "url": "https://cms.gov/Regulations-and-Guidance/Guidance/Manuals/Downloads/bp102c07.pdf"
}