{
  "chunk_id": "hha-ffs__bp102c07_pdf__551d41d9a2__p8__chunk_1",
  "source_document": "data/raw/assets/pdf/551d41d9a2e0df08a63c3215d57d55efb3708dd1.pdf",
  "page": 8,
  "text": "treatment & evaluation of a surgical wound(s); \nassessment, treatment & evaluation of non-surgical wounds, ulcers, \nburns, and other lesions \n\nBehavioral Health Care Assessment, treatment & evaluation of psychiatric and substance \nabuse conditions \n\nComplex Nursing Interventions Assessment, treatment & evaluation of complex medical & surgical \nconditions including IV, TPN, enteral nutrition, ventilator, and \nostomies \nMedication Management, Teaching and \nAssessment (MMTA) \n MMTA –Surgical",
  "dataset": "hha-ffs",
  "url": "https://cms.gov/Regulations-and-Guidance/Guidance/Manuals/Downloads/bp102c07.pdf"
}