{
  "chunk_id": "hha-ffs__bp102c07_pdf__551d41d9a2__p25__chunk_5",
  "source_document": "data/raw/assets/pdf/551d41d9a2e0df08a63c3215d57d55efb3708dd1.pdf",
  "page": 25,
  "text": "than in the home. \n\nSome examples of homebound patients that illustrate the factors used to determine \nwhether a homebound condition exists are listed below. \n • A patient paralyzed from a stroke who is confined to a wheelchair or requires the \naid of crutches in order to walk. \n\n• A patient who is blind or senile and requires the assistance of another person in \nleaving their place of residence. \n\n• A patient who has lost the use of their upper extremities and, therefore, is unable \nto open",
  "dataset": "hha-ffs",
  "url": "https://cms.gov/Regulations-and-Guidance/Guidance/Manuals/Downloads/bp102c07.pdf"
}