{
  "chunk_id": "hha-ffs__bp102c07_pdf__551d41d9a2__p11__chunk_3",
  "source_document": "data/raw/assets/pdf/551d41d9a2e0df08a63c3215d57d55efb3708dd1.pdf",
  "page": 11,
  "text": "group are paid the wage-adjusted per \nvisit amount for each of the visits rendered instead of the full 30-day period payment \namount. The national per visit amounts by discipline (skilled nursing, home health aide, \nphysical therapy, speech-language pathology, occupational therapy, and medical social \nservices) are updated and published annually by the applicable market basket for each \nvisit type. To offset the full cost of longer, initial visits in some LUPA periods, the \nLUPA payment is",
  "dataset": "hha-ffs",
  "url": "https://cms.gov/Regulations-and-Guidance/Guidance/Manuals/Downloads/bp102c07.pdf"
}