{
  "chunk_id": "hha-ffs__bp102c07_pdf__551d41d9a2__p75__chunk_4",
  "source_document": "data/raw/assets/pdf/551d41d9a2e0df08a63c3215d57d55efb3708dd1.pdf",
  "page": 75,
  "text": "required to perform the \nprocedures, would be covered speech-language pathology services. \n\n6. The services of a speech-language pathologist to assist patients with aphasia in \nrehabilitation of speech and language skills are covered when needed by a patient. \n\n7. The services of a speech-language pathologist to assist patients with voice disorders to \ndevelop proper control of the vocal and respiratory systems for correct voice \nproduction are covered when needed by a patient. \n\n40.2.4 -",
  "dataset": "hha-ffs",
  "url": "https://cms.gov/Regulations-and-Guidance/Guidance/Manuals/Downloads/bp102c07.pdf"
}