{
  "chunk_id": "hha-ffs__bp102c07_pdf__551d41d9a2__p80__chunk_2",
  "source_document": "data/raw/assets/pdf/551d41d9a2e0df08a63c3215d57d55efb3708dd1.pdf",
  "page": 80,
  "text": "hair on the other two visits each week. Only two visits are reasonable and necessary \nsince the services could have been provided in the course of two visits. \n\nEXAMPLE 3: \n\nA physician ordered seven home health aide visits per week for personal care for a bed-\nbound, incontinent patient. All visits are reasonable and necessary because the patient \nhas extensive personal care needs. \n\nEXAMPLE 4: \n\nA patient with a well-established colostomy forgets to change the bag regularly and has",
  "dataset": "hha-ffs",
  "url": "https://cms.gov/Regulations-and-Guidance/Guidance/Manuals/Downloads/bp102c07.pdf"
}