{
  "chunk_id": "hha-ffs__bp102c07_pdf__551d41d9a2__p65__chunk_2",
  "source_document": "data/raw/assets/pdf/551d41d9a2e0df08a63c3215d57d55efb3708dd1.pdf",
  "page": 65,
  "text": "01-07-14) \nA3-3118.2, HHA-205.2 \n\nTo be covered as skilled therapy, the services must require the skills of a qualified \ntherapist and must be reasonable and necessary for the treatment of the patient’s illness or \ninjury as discussed below. Coverage does not turn on the presence or absence of an \nindividual’s potential for improvement, but rather on the beneficiary’s need for skilled \ncare. \n\n40.2.1 - General Principles Governing Reasonable and Necessary \nPhysical Therapy, Speech-Language",
  "dataset": "hha-ffs",
  "url": "https://cms.gov/Regulations-and-Guidance/Guidance/Manuals/Downloads/bp102c07.pdf"
}