{
  "chunk_id": "ip-ffs__codebook-ffs-claims_pdf__a4af628b5a__p149__chunk_2",
  "source_document": "data/raw/assets/pdf/a4af628b5ad494c93baa8921ab4d55ef29217d67.pdf",
  "page": 149,
  "text": "Intermediate care \n— level III) \n8 = Swing bed \n\nFor facility type code 7 (clinics): \n\n1 = Rural Health Clinic (RHC) \n2 = Hospital based or independent \nrenal dialysis facility \n3 = Free-standing provider based \nfederally qualified health center \n(FQHC) \n4 = Other Rehabilitation Facility (ORF) \n 5 = Comprehensive Rehabilitation Center \n(CORF) \n6 = Community Mental Health Center \n(CMHC) \n7 = Federally Qualified Health Center \n(FQHC) \n\nFor facility type code 8 (special facility): \n\n1 = Hospice",
  "dataset": "ip-ffs",
  "url": "https://www2.ccwdata.org/documents/10280/19022436/codebook-ffs-claims.pdf"
}