{
  "chunk_id": "ip-ffs__codebook-ffs-claims_pdf__a4af628b5a__p238__chunk_9",
  "source_document": "data/raw/assets/pdf/a4af628b5ad494c93baa8921ab4d55ef29217d67.pdf",
  "page": 238,
  "text": "psychological \ntesting \n58 = Non-residential opioid treatment facility (eff. 1/2020) \n59 = Unassigned. N/A \n60 = Mass immunization center — location where providers administer pneumococcal pneumonia and \ninfluenza virus vaccinations and submit these services as electronic media claims, paper claims, or \nusing the roster billing method. This generally takes place in a mass immunization setting, such \nas, a public health center, pharmacy, or mall but may include a physician office setting \n61 =",
  "dataset": "ip-ffs",
  "url": "https://www2.ccwdata.org/documents/10280/19022436/codebook-ffs-claims.pdf"
}