{
  "chunk_id": "ip-ffs__codebook-ffs-claims_pdf__a4af628b5a__p413__chunk_1",
  "source_document": "data/raw/assets/pdf/a4af628b5ad494c93baa8921ab4d55ef29217d67.pdf",
  "page": 413,
  "text": "employer identification number (EIN) or social security number (SSN). \n\nSHORT NAME: TAX_NUM \n\nLONG NAME: TAX_NUM \n\nTYPE: CHAR \n\nLENGTH: 10 \n\nSOURCE: NCH \n\nVALUES: — \n\nCOMMENT: For DME claims, all 10 digits are populated. The first 9 digits represent the EIN or SSN, and the final \n(rightmost) tenth digit indicates the type of provider ID that is used (reference the \nDMERC_LINE_SUPPLR_TYPE_CD for these values). For all other claim types, only 9 digits of the field \nare populated. \n ^ Back to TOC ^",
  "dataset": "ip-ffs",
  "url": "https://www2.ccwdata.org/documents/10280/19022436/codebook-ffs-claims.pdf"
}