{
  "chunk_id": "mbsf-base-v2__codebook-mbsf-abcd-v2_pdf__88dec20615__p29__chunk_2",
  "source_document": "data/raw/assets/pdf/88dec20615b0691efc1812370c27a4f1825aa109.pdf",
  "page": 29,
  "text": "sharing group data \n\nCOMMENT: Beneficiaries who are deemed eligible for fully subsidized Part D coverage due to dual enrollment in \nMedicare-Medicaid have a cost-share group code of 01, 02, or 03 for the month. Beneficiaries who are \nnot dually enrolled but are eligible for a full LIS subsidy are classified as 04. Other beneficiaries who \nare eligible for the LIS but do not receive a full subsidy have a 05, 06, 07, or 08. The remaining values \nindicate that the individual is not eligible for",
  "dataset": "mbsf-base-v2",
  "url": "https://www2.ccwdata.org/documents/10280/19022436/codebook-mbsf-abcd-v2.pdf"
}