{
  "chunk_id": "mbsf-27-cc__chunk_0",
  "source_document": "data/raw/html/dataset_page/6699b0dfb0111bbb6b6b3146eba42feed4fe9587.html",
  "page": null,
  "text": "Skip to main content\n\nReminder: DUA and VRDC access needs to be extended or renewed annually. Read more.\n\nTop Menu\n\n A-Z Glossary\n\n Contact Us\n\n Navigation Menu\n\n Find CMS Data Files\n\n Request CMS Data Files\n\n Search Data Variables\n\n Learn About CMS Data\n\nMaster Beneficiary Summary File 27 CCW Chronic Conditions\n\n View Data Documentation\n\nThe 27 CCW Chronic Conditions segment of the Master Beneficiary Summary File (MBSF) flags each Medicare beneficiary for the presence of one of 27 specific",
  "dataset": "mbsf-27-cc",
  "url": "https://resdac.org/cms-data/files/mbsf-27-cc?page=1"
}