{
  "chunk_id": "mbsf-cc__ccw-condition-categories-impact-of-transition-from-27-to-30_pdf__397fc86416__p17__chunk_2",
  "source_document": "data/raw/assets/pdf/397fc86416f84595f04fdcac403dfce16ac06e4d.pdf",
  "page": 17,
  "text": "files, 2017 \n\nCondition “Ever” date in \n27 CCW or 30 \nCCW \n(total \nbeneficiaries) \n In both 27 \nCCW and 30 \nCCW \n(benes) \n Both \n(%) In 27 CCW \nonly \n(benes) \n 27 \nCCW \n(%) \n In 30 CCW \nonly \n(benes) \n 30 \nCCW \n(%) \n\nAcute Myocardial \nInfarction 1,969,802 590,072 30.0% 1,290,967 65.5% 88,763 4.5% \n\nAlzheimer's Disease 2,093,499 1,136,926 54.3% 956,573 45.7% 0 0.0% \nAnemia 21,041,243 7,835,209 37.2% 13,201,168 62.7% 4,866 0.0% \nAsthma 6,115,770 2,828,844 46.3% 3,246,804 53.1% 40,122 0.7% \nAtrial",
  "dataset": "mbsf-cc",
  "url": "https://www2.ccwdata.org/documents/10280/19002256/ccw-condition-categories-impact-of-transition-from-27-to-30.pdf"
}