{
  "chunk_id": "mbsf-base-v2__chunk_3",
  "source_document": "data/raw/html/dataset_page/7f6620be0130d2512c41c119d6426f5eb0feab09.html",
  "page": null,
  "text": "quarterly 2024 MBSF base data will receive the current version. The current MBSF Base A/B/C/D file will no longer be produced starting with annual 2024 data. For more detailed information about the MBSF data and enhancements, reference the CCW Medicare Administrative Data User Guide and Codebook.\nFour additional segments are available for order with this file:\nChronic Conditions\nOther Chronic Conditions\nCost and Use\nNational Death Index (NDI)\n\nProgram: \nMedicare\nCategory: \nBeneficiary",
  "dataset": "mbsf-base-v2",
  "url": "https://resdac.org/cms-data/files/mbsf-base-v2?page=1"
}