{
  "chunk_id": "mbsf-base__codebook-mbsf-abcd_pdf__3ce60d9c5a__p1__chunk_0",
  "source_document": "data/raw/assets/pdf/3ce60d9c5a3b97f691686c5fdd76b1f633f07612.pdf",
  "page": 1,
  "text": "Chronic Conditions Warehouse \nYour source for national CMS Medicare and Medicaid research data \n\nChronic Conditions Warehouse Virtual Research Data Center \n\nMedicare Beneficiary Summary File (MBSF) \nBase with Medicare Part A, B, C, and D Codebook \n\nMAY 2026 │ VERSION 1.9",
  "dataset": "mbsf-base",
  "url": "https://www2.ccwdata.org/documents/10280/19022436/codebook-mbsf-abcd.pdf"
}