{
  "chunk_id": "mds-30__record-layout-mds-3-0_xlsx__55bd4e4e66__s1__chunk_230",
  "source_document": "data/raw/assets/xlsx/55bd4e4e66fb4eda32461631b671f7a2d6770e14.xlsx",
  "page": 1,
  "text": "steady, only able to stabilize with human assistance\r\n8=Activity did not occur discontinued 09/30/2023\n241 G0300B_BAL_WLKG_CD G0300B_BAL_WLKG_CD G0300B Balance During Walking Code CHAR 1 The data in this column identifies the resident's balance while walking (with assistive device if used). -=Not assessed/no information\r\n0=Steady at all times\r\n1=Not steady, but able to stabilize without human assistance\r\n2=Not steady, only able to stabilize with human assistance\r\n8=Activity did not occur",
  "dataset": "mds-30",
  "url": "https://www2.ccwdata.org/documents/10280/19022436/record-layout-mds-3-0.xlsx"
}