{
  "chunk_id": "mds-sb-20__record-layout-sb-2-0_xlsx__b75622ce61__s1__chunk_115",
  "source_document": "data/raw/assets/xlsx/b75622ce6136dda733759e7be67a80bd728fb9cc.xlsx",
  "page": 1,
  "text": "part around a fixed point or joint through the patient's available range of motion.\n151 P3B P3B_NR_MOTION_ACTV 39b(P3b)Nursing Rehab: Range of Motion (Active) CHAR 1 Indicates the extent to which the patient received active range of motion nursing rehabilitation intervention. Range of moition exercise is a program of exercises performed by the patient, with cueing or supervision by staff, that are planned, scheduled, and documented.\n152 P3C P3C_NR_SPLINT 39c(P3c)Nursing Rehab: Splint/Brace",
  "dataset": "mds-sb-20",
  "url": "https://www2.ccwdata.org/documents/10280/19022436/record-layout-sb-2-0.xlsx"
}