{
  "chunk_id": "mds-30__record-layout-mds-3-0_xlsx__55bd4e4e66__s1__chunk_261",
  "source_document": "data/raw/assets/xlsx/55bd4e4e66fb4eda32461631b671f7a2d6770e14.xlsx",
  "page": 1,
  "text": "information\r\n0=Not checked (No)\r\n1=Checked (Yes)\n276 I1200_GERD_CD I1200_GERD_CD I1200 Active Diagnoses: Gastroesophageal Reflux Disease (GERD) Code CHAR 1 The data in this column indicates whether the resident had an active diagnosis of gastoresophageal reflux disease (GERD) or ulcer (e.g., esophageal, gasric and peptic ulcers) in the last seven days. -=Not assessed/no information\r\n0=Not checked (No)\r\n1=Checked (Yes)\n277 I1300_ULCRTV_CLTS_CD I1300_ULCRTV_CLTS_CD I1300 Active Diagnoses:",
  "dataset": "mds-30",
  "url": "https://www2.ccwdata.org/documents/10280/19022436/record-layout-mds-3-0.xlsx"
}