{
  "chunk_id": "mds-30__record-layout-mds-3-0_xlsx__55bd4e4e66__s1__chunk_410",
  "source_document": "data/raw/assets/xlsx/55bd4e4e66fb4eda32461631b671f7a2d6770e14.xlsx",
  "page": 1,
  "text": "M1200I_APLCTN_DRSNG_FOOT_CD M1200I Skin and Ulcer Treatments: Application Dressings to Foot Code CHAR 1 The data in this column indicates that dressings (with or without topical medications) are applied to the body other than feet. -=Not assessed/no information\r\n0=Not checked (No)\r\n1=Checked (Yes)\n458 M1200Z_NO_SKIN_TRMNT_CD M1200Z_NO_SKIN_TRMNT_CD M1200Z Skin and Ulcer Treatments: None of Above Code CHAR 1 The data in this column indicates that none of the above skin or ulcer treatments were",
  "dataset": "mds-30",
  "url": "https://www2.ccwdata.org/documents/10280/19022436/record-layout-mds-3-0.xlsx"
}