{
  "chunk_id": "mds-sb-20__record-layout-sb-2-0_xlsx__b75622ce61__s1__chunk_16",
  "source_document": "data/raw/assets/xlsx/b75622ce6136dda733759e7be67a80bd728fb9cc.xlsx",
  "page": 1,
  "text": "category: Hispanic or Latino.\n34 _5E ETHNCTY_NTV_HI_PCFC_ISLNDR_SW (5e)Race: Native Hawaiian or other Pacific Islander CHAR 1 The patient's race or ethnic category: Native Hawaiian or other Pacific Islander.\n35 _5F ETHNCTY_WHT_SW (5f)Race: White CHAR 1 The patient's race or ethnic category: White\n36 _11C ASMT_OMRA_SW (11c) OMRA Assessment CHAR 1 The OMRA (Other medicare Required Assessment) must be completed only if the patient was in a RUG-III Rehabilitation classification and will continue to",
  "dataset": "mds-sb-20",
  "url": "https://www2.ccwdata.org/documents/10280/19022436/record-layout-sb-2-0.xlsx"
}