{
  "chunk_id": "mds-20__record-layout-mds-2-0_xlsx__3217847391__s1__chunk_122",
  "source_document": "data/raw/assets/xlsx/3217847391ddeaf11fa2cd9c65f18561d39d28aa.xlsx",
  "page": 1,
  "text": "No, 1 = Yes, \"-\" = Unknown, -2 = Space.\n205 F3D F3D_NONE_ABOVE (F3D) None of Above Past Roles CHAR 1 Psychosocial well-being: past roles - none of above. 0 = No, 1 = Yes, \"-\" = Unknown, -2 = Space.\n206 G1AA G1AA_SELF_BED (G1AA) Bed Mobility Self Performance CHAR 1 Physical functioning and structural problems: bed mobility - ADL self-performance \"-\" = Unknown, 0 = Independent - No help or oversight -OR- Help/oversight provided only 1 or 2 times during last 7 days, 1 = Supervision - Oversight,",
  "dataset": "mds-20",
  "url": "https://www2.ccwdata.org/documents/10280/19022436/record-layout-mds-2-0.xlsx"
}