{
  "chunk_id": "mds-30__record-layout-mds-3-0_xlsx__55bd4e4e66__s1__chunk_214",
  "source_document": "data/raw/assets/xlsx/55bd4e4e66fb4eda32461631b671f7a2d6770e14.xlsx",
  "page": 1,
  "text": "help from staff\r\n 1=Setup help only\r\n 2=One person physical assist\r\n 3=Two+ persons physical assist\r\n 8=ADL activity itself did not occur or family and/or facility staff provided care 100% of the time for that activity over the entire 7-day period discontinued 09/30/2023\n232 G0110H1_EATG_SELF_CD G0110H1_EATG_SELF_CD G0110H1 ADL Assistance: Eating Self Performance Code CHAR 1 The data in this column identifies the resident's self-performance ability with eating. -=Not assessed/no",
  "dataset": "mds-30",
  "url": "https://www2.ccwdata.org/documents/10280/19022436/record-layout-mds-3-0.xlsx"
}