{
  "chunk_id": "medpar__codebook-medpar_pdf__01880a8f13__p111__chunk_0",
  "source_document": "data/raw/assets/pdf/01880a8f130acdc0b26ba14dd05f81632589ce24.pdf",
  "page": 111,
  "text": "Chronic Conditions Warehouse Virtual Research Data Center \nMedPAR Codebook │ April 2025 │ V 4.2 95 \n\nFICARR_IDENT_NUM \n\nLABEL: Fiscal Intermediary (FI) ID Number \n\nDESCRIPTION: The identification of the fiscal intermediary (FI; CMS contractors which are currently known as Medicare \nadministrative contractors [MACs]) processing the beneficiary's claims related to the stay. \n\nSHORT NAME: FICARR \n\nLONG NAME: FICARR_IDENT_NUM \n\nTYPE: CHAR \n\nLENGTH: 5 \n\nSOURCE: NCH \n\nVALUES: XXXXX \n\nCOMMENT: This",
  "dataset": "medpar",
  "url": "https://www2.ccwdata.org/documents/10280/19022436/Codebook-MedPAR.pdf"
}