{
  "chunk_id": "mmleads-2__record-layout-mmleads-2006-2012_xlsx__44dbf84b20__s2__chunk_38",
  "source_document": "data/raw/assets/xlsx/44dbf84b2079bde113ba3342dc52d79adaaab07f.xlsx",
  "page": 2,
  "text": "Hyperlipidemia - Medicaid Only Claims, First Ever Occurrence Date date - MM/DD/YYYY\n HYPTEN_COMBINED Hypertension - Combined Medicare Medicaid Claims 0 - Claims and FFS not met\r\n1 - Claims met, not FFS\r\n2 - Claims not met, FFS\r\n3 - Claims met and FFS\n HYPTEN_MEDICARE Hypertension - Medicare Only Claims 0 - Claims and FFS not met\r\n1 - Claims met, not FFS\r\n2 - Claims not met, FFS\r\n3 - Claims met and FFS\n HYPTEN_MEDICAID Hypertension - Medicaid Only Claims 0 - Claims and FFS not met\r\n1 - Claims",
  "dataset": "mmleads-2",
  "url": "https://www2.ccwdata.org/documents/10280/19022436/record-layout-mmleads-2006-2012.xlsx"
}