{
  "chunk_id": "mmleads-3__record-layout-mmleads_xlsx__22736b9e52__s1__chunk_22",
  "source_document": "data/raw/assets/xlsx/22736b9e5259750d16e7bb38f8963a293e7b3e9c.xlsx",
  "page": 1,
  "text": "Entitlement/Buy-In Indicator - November Char 1\n110 MDCR_FFS_MEDICAL_11 Medicare - Fee-for-Service Medical Coverage Indicator - November Num 8\n111 MDCR_DUAL_STUS_CD_12 Medicare - Medicaid Dual Eligibility Code - December Char 2\n112 MDCR_BUYIN_12 Medicare - Entitlement/Buy-In Indicator - December Char 1\n113 MDCR_FFS_MEDICAL_12 Medicare - Fee-for-Service Medical Coverage Indicator - December Num 8\n114 MDCD_STATE_CD_01 Medicaid - State Alpha Abbreviation - January Char 2\n115 MDCD_STATE_CD_02",
  "dataset": "mmleads-3",
  "url": "https://www2.ccwdata.org/documents/10280/19022436/record-layout-mmleads.xlsx"
}