{
  "chunk_id": "mmleads-3__record-layout-mmleads_xlsx__22736b9e52__s1__chunk_9",
  "source_document": "data/raw/assets/xlsx/22736b9e5259750d16e7bb38f8963a293e7b3e9c.xlsx",
  "page": 1,
  "text": "Management (PCCM) Months Num 3\n49 MDCD_HIO_COV_MOS Medicaid - Health Insuring Organization (HIO) Months Num 3\n50 MDCD_PHP_COV_MOS Medicaid - Prepaid Inpatient or Ambulatory Hlth Plan (PIHP / PAHP) Months Num 8\n51 MDCD_LTC_COV_MOS Medicaid - Long-Term Care Prepaid Inpatient Hlth Plan (PIHP) Months Num 3\n52 MDCD_BEHAVIORAL_COV_MOS Medicaid - Managed Care Mental Health or Substance Abuse Coverage Months Num 8\n53 MDCD_DENTAL_COV_MOS Medicaid - Managed Care Dental Coverage Months Num 3\n54",
  "dataset": "mmleads-3",
  "url": "https://www2.ccwdata.org/documents/10280/19022436/record-layout-mmleads.xlsx"
}