{
  "chunk_id": "mmleads-3__codebook-mmleads_pdf__536286800b__p114__chunk_1",
  "source_document": "data/raw/assets/pdf/536286800bad660e7af16072eb5a63475d8835f9.pdf",
  "page": 114,
  "text": "equipment (DME). Note that only fee-for-service (FFS) claims are included. \n\nTYPE: NUM \n\nLENGTH: 8 \n\nSOURCE: Medicare Carrier and Durable Medical Equipment (DME) Claims files (derived) \n\nVALUES: $ \n\nCOMMENT: CCW calculates this variable as the sum of all CLM_PMT_AMT from the Carrier and DME claims. \n\n^ Back to TOC ^",
  "dataset": "mmleads-3",
  "url": "https://www2.ccwdata.org/documents/10280/19022436/codebook-mmleads.pdf"
}