{
  "chunk_id": "mmleads-3__codebook-mmleads_pdf__536286800b__p28__chunk_5",
  "source_document": "data/raw/assets/pdf/536286800bad660e7af16072eb5a63475d8835f9.pdf",
  "page": 28,
  "text": "to Work Basic Group \n49 = Ticket to Work Medical Improvements Group \n50 = Family Opportunity Act Children with Disabilities \n51 = Individuals Eligible for Home and Community-Based Services \n52 = Individuals Eligible for Home and Community-Based Services — Special Income Level \n53 = Medically Needy Pregnant Women \n54 = Medically Needy Children > Age 18 \n55 = Medically Needy Children Age 18–20 \n56 = Medically Needy Parents and Other Caretakers \n59 = Medically Needy Aged, Blind or Disabled \n60 =",
  "dataset": "mmleads-3",
  "url": "https://www2.ccwdata.org/documents/10280/19022436/codebook-mmleads.pdf"
}