{
  "chunk_id": "oasis__record-layout-oasis_xlsx__2102fe8aba__s1__chunk_887",
  "source_document": "data/raw/assets/xlsx/2102fe8aba60550816b99a0ae8ceb566105ee9b5.xlsx",
  "page": 1,
  "text": "the last 2 weeks, the patient has had little interest or pleasure in doing things. 0. No\r\n1. Yes \r\n9. No response CHAR 1 x\nD0150A2_LTTL_INTRST_FREQ_CD Mood: Little interest/pleasure doing things: Freq Indicates the frequency, over the last 2 weeks, the patient has had little interest or pleasure in doing things. 0. Never or 1 day \r\n1. 2-6 days (several days) \r\n2. 7-11 days (half or more of the days) \r\n3. 12-14 days (nearly every day) CHAR 1 x\nD0150B1_DOWN_DPRSD_CD Mood: Feeling down, depressed,",
  "dataset": "oasis",
  "url": "https://www2.ccwdata.org/documents/10280/19022436/record-layout-oasis.xlsx"
}