{
  "chunk_id": "pde__codebook-pde_pdf__c8d3789e9b__p15__chunk_2",
  "source_document": "data/raw/assets/pdf/c8d3789e9b9a3e36ec93e4d39d180a1ab4ef52ce.pdf",
  "page": 15,
  "text": "point \nN = Attachment Point met; TrOOP subsequently reduced below the OOP threshold due to payment \namounts from non-EGWP other payers reported in PLRO (reported by EGWPs only) \nBlank = Attachment point not met \n\nCOMMENT: This variable was required for all PDEs through the end of 2010, and became optional starting in 2011. \n\nThe value may differ from the more detailed BENEFIT_PHASE variable, which is a CCW-derived field \nthat is available for all years. \n ^ Back to TOC ^",
  "dataset": "pde",
  "url": "https://www2.ccwdata.org/documents/10280/19022436/codebook-pde.pdf"
}