{
  "chunk_id": "plan-characteristics__record-layout-ptd-plan-char-2007-2014_xlsx__a9368c7fc4__s3__chunk_3",
  "source_document": "data/raw/assets/xlsx/a9368c7fc4e008ebd1c2dcab08f589f5cc115ccc.xlsx",
  "page": 3,
  "text": "Pre-ICL In-Network Pharmacy Coinsurance for 3 month supply NUM 8 X X X X X X X X\nPRE_ICL_INP_COINS_OS Pre-ICL In-Network Pharmacy Coinsurance for other days supply NUM 8 X X X X X X - -\nPRE_ICL_INP_COINS_AVG_1M Pre-ICL In-Network Pharmacy Average Expected Coinsurance for 1 month Supply NUM 8 - - - - - - X X\nPRE_ICL_INPP_COINS_1M Pre-ICL In-Network Preferred Pharmacy Coinsurance for 1 month Supply NUM 8 X X X X X X X X\nPRE_ICL_INPP_COINS_2M re-ICL Coinsurance In-Network Preferred Pharmacy",
  "dataset": "plan-characteristics",
  "url": "https://www2.ccwdata.org/documents/10280/19022436/record-layout-ptd-plan-char-2007-2014.xlsx"
}