{
  "chunk_id": "plan-characteristics__codebook-plan-char_pdf__77e437e4fb__p74__chunk_0",
  "source_document": "data/raw/assets/pdf/77e437e4fbf75223d4afb45fb37a8a975a86839b.pdf",
  "page": 74,
  "text": "Chronic Conditions Warehouse Virtual Research Data Center \nMedicare Plan Characteristics Codebook │ October 2025 │ V 1.7 60 \n\nEGWP_INDICATOR \n\nLABEL: Employer Group Waiver Plan (EGWP) Indicator \n\nDESCRIPTION: This variable indicates whether the plan benefit package is an employer group waiver plan (EGWP). \n\nEGWP plans are not open to general enrollment but rather are offered to beneficiaries through an \nemployer group. \n\nTYPE: CHAR \n\nLENGTH: 1 \n\nSOURCE: CMS (HPMS files) \n\nVALUES: Y = Yes \nN =",
  "dataset": "plan-characteristics",
  "url": "https://www2.ccwdata.org/documents/10280/19022436/codebook-plan-char.pdf"
}