{
  "chunk_id": "taf-de__codebook-taf-demographic-eligibility_pdf__7a48be3f0d__p115__chunk_1",
  "source_document": "data/raw/assets/pdf/7a48be3f0d3c4224b3129bd4e6af2eec1975b637.pdf",
  "page": 115,
  "text": "group that covered their Medicaid or CHIP benefits. \n\nSHORT NAME: FPL_PCT \n\nLONG NAME: FPL_PCT \n\nTYPE: NUM \n\nLENGTH: 3 \n\nFILE(S): Annual DE base \n\nSOURCE: T-MSIS annual demographic and eligibility TAF \n\nVALUES: 0–400 (whole numbers) or null/missing (income not required by the eligibility group for which they \nwere determined eligible) \n\nCOMMENT: This field is new, starting with the 2023 TAF DE RIF. It is not populated in data for earlier service years. \n\nIncome is not applicable for the",
  "dataset": "taf-de",
  "url": "https://www2.ccwdata.org/documents/10280/19022436/codebook-taf-demographic-eligibility.pdf"
}