{
  "chunk_id": "taf-apr__codebook-taf-annual-provider_pdf__de0c89017c__p154__chunk_2",
  "source_document": "data/raw/assets/pdf/de0c89017c1d3e10d2c3fa782cf1871880f29b65.pdf",
  "page": 154,
  "text": "of Veterans Affairs (VA) pharmacy \n332800000X: Indian Health Service/Tribal/Urban Indian Health (I/T/U) Pharmacy \n332900000X: Non-pharmacy dispensing site \n332B00000X: Durable medical equipment and medical supplies \n332BC3200X: Durable medical equipment and medical supplies — customized equipment \n332BD1200X: Durable medical equipment and medical supplies — Dialysis equipment and supplies \n332BN1400X: Durable medical equipment and medical supplies — Nursing facility supplies \n332BP3500X:",
  "dataset": "taf-apr",
  "url": "https://www2.ccwdata.org/documents/10280/19022436/codebook-taf-annual-provider.pdf"
}