{
  "chunk_id": "taf-de__codebook-taf-demographic-eligibility_pdf__7a48be3f0d__p274__chunk_2",
  "source_document": "data/raw/assets/pdf/7a48be3f0d3c4224b3129bd4e6af2eec1975b637.pdf",
  "page": 274,
  "text": "RSTRCTD_BNFTS_CD_04 \nRSTRCTD_BNFTS_CD_05 \nRSTRCTD_BNFTS_CD_06 \n RSTRCTD_BNFTS_CD_07 \nRSTRCTD_BNFTS_CD_08 \nRSTRCTD_BNFTS_CD_09 \nRSTRCTD_BNFTS_CD_10 \nRSTRCTD_BNFTS_CD_11 \nRSTRCTD_BNFTS_CD_12 \n\nLONG NAME: RSTRCTD_BNFTS_CD_01 \nRSTRCTD_BNFTS_CD_02 \nRSTRCTD_BNFTS_CD_03 \nRSTRCTD_BNFTS_CD_04 \nRSTRCTD_BNFTS_CD_05 \nRSTRCTD_BNFTS_CD_06 \n RSTRCTD_BNFTS_CD_07 \nRSTRCTD_BNFTS_CD_08 \nRSTRCTD_BNFTS_CD_09 \nRSTRCTD_BNFTS_CD_10 \nRSTRCTD_BNFTS_CD_11 \nRSTRCTD_BNFTS_CD_12 \n\nTYPE: CHAR \n\nLENGTH: 1 \n\nFILE(S): Annual",
  "dataset": "taf-de",
  "url": "https://www2.ccwdata.org/documents/10280/19022436/codebook-taf-demographic-eligibility.pdf"
}