{
  "chunk_id": "taf-de__codebook-taf-demographic-eligibility_pdf__7a48be3f0d__p258__chunk_1",
  "source_document": "data/raw/assets/pdf/7a48be3f0d3c4224b3129bd4e6af2eec1975b637.pdf",
  "page": 258,
  "text": "as the Medicaid Statistical Information \nSystem Identifier (MSIS_ID). \n\nSHORT NAME: MSIS_ID \n\nLONG NAME: MSIS_ID \n\nTYPE: CHAR \n\nLENGTH: 32 \n\nFILE(S): All demographic and eligibility \n\nSOURCE: T-MSIS annual demographic and eligibility TAF \n\nVALUES: Alphanumeric character string, 32 characters \n\n(Ex: 9Q81866B302C768A539BBE79FFB835FB) \n\nNull/missing = source value is missing or unknown \n\nCOMMENT: The MSIS ID is unique only within a state for a year; a beneficiary’s MSIS ID may change",
  "dataset": "taf-de",
  "url": "https://www2.ccwdata.org/documents/10280/19022436/codebook-taf-demographic-eligibility.pdf"
}