{
  "chunk_id": "taf-ip__codebook-taf-claims_pdf__3a7e50ca3f__p155__chunk_5",
  "source_document": "data/raw/assets/pdf/3a7e50ca3fea9874a59b75c2b53d874e249d4e08.pdf",
  "page": 155,
  "text": "business. Data \nusers who do have access to those dollar amounts should avoid double counting the amount paid \nby the state or their fiscal agent to managed care plans AND the amount paid by the managed \ncare plan to providers. \n ^ Back to TOC ^",
  "dataset": "taf-ip",
  "url": "https://www2.ccwdata.org/documents/10280/19022436/codebook-taf-claims.pdf"
}