{
  "chunk_id": "taf-de__codebook-taf-demographic-eligibility_pdf__7a48be3f0d__p100__chunk_2",
  "source_document": "data/raw/assets/pdf/7a48be3f0d3c4224b3129bd4e6af2eec1975b637.pdf",
  "page": 100,
  "text": "state \n16 = Voluntary request for termination \n17 = Lack of verifications \n18 = Fraud \n19 = Suspension due to incarceration \n20 = Residence in an institution for mental disease (IMD) \n21 = Suspension/Termination with reason unknown \n22 = Other \n23 = Terminated due to incorrect granting of eligibility (e.g., someone is given eligibility in error and \nthen eligibility is retracted/terminated) \n24 = Household or family composition criteria not met (e.g., someone was incorrectly included or",
  "dataset": "taf-de",
  "url": "https://www2.ccwdata.org/documents/10280/19022436/codebook-taf-demographic-eligibility.pdf"
}