{
  "chunk_id": "vm-beneficiary__record-layout-value-modifier-bene-level-rif-perf-year-2016_xlsx__761b9bb766__s1__chunk_41",
  "source_document": "data/raw/assets/xlsx/761b9bb766f9b4e05e452ed8077ccfa7e6d9e26d.xlsx",
  "page": 1,
  "text": "the given practice category 57 Num 8 Populated only for records with Inpatient_stay not equal to missing\nTOTAL_PA Total costs for other post-acute care services (excluding hospice) Per capita cost for attributed beneficiary, Post-Acute Services category 58 Num 8 Populated only for records with Inpatient_stay not equal to missing\nOP_THERAPY Total costs for outpatient physical therapy, occupational therapy, or speech and language pathology therapy Per capita cost for attributed beneficiary,",
  "dataset": "vm-beneficiary",
  "url": "https://resdac.org/sites/datadocumentation.resdac.org/files/2025-02/record-layout-value-modifier-bene-level-rif-perf-year-2016.xlsx"
}