{
  "chunk_id": "vm-practice__record-layout-value-modifier-practice-level-rif-perf-year-2016_xlsx__e75ad5dc90__s1__chunk_45",
  "source_document": "data/raw/assets/xlsx/e75ad5dc90d8b0bcd7b35ea5b41e8e51e49d04b1.xlsx",
  "page": 1,
  "text": "practice in PECOS Number of eligible professionals in practice identified via PECOS 51 Num 8 \nPHYS_COUNT Num of physicians in claims Number of physicians who billed Part B claims under practice 52 Num 8 \nPECOS_NON_PHYS_COUNT Num of nonphysician EPs associated with practice in PECOS Number of nonphysician eligible professionals in practice identified via PECOS 53 Num 8 \nPECOS_NON_PHYS_PCT Percent of PECOS EPs who are nonphysicians Percent of nonphysician eligible professionals in practice",
  "dataset": "vm-practice",
  "url": "https://resdac.org/sites/datadocumentation.resdac.org/files/2025-02/record-layout-value-modifier-practice-level-rif-perf-year-2016.xlsx"
}