{
  "chunk_id": "vm-practice__record-layout-value-modifier-practice-level-rif-perf-year-2016_xlsx__e75ad5dc90__s1__chunk_1830",
  "source_document": "data/raw/assets/xlsx/e75ad5dc90d8b0bcd7b35ea5b41e8e51e49d04b1.xlsx",
  "page": 1,
  "text": "Denominator for PQRS 24 (IEP Non-eCQM) Denominator for PQRS 24 (IEP Non-eCQM) (Communication and Care Coordination) 2740 Num 8 \nDENOM_24PQRS_REG Denominator for PQRS 24 (Registry) Denominator for PQRS 24 (Registry) (Communication and Care Coordination) 2741 Num 8 \nDENOM_250PQRS_IEP_NEHR Denominator for PQRS 250 (IEP Non-eCQM) Denominator for PQRS 250 (IEP Non-eCQM) (Effective Clinical Care) 2742 Num 8 \nDENOM_250PQRS_REG Denominator for PQRS 250 (Registry) Denominator for PQRS 250 (Registry)",
  "dataset": "vm-practice",
  "url": "https://resdac.org/sites/datadocumentation.resdac.org/files/2025-02/record-layout-value-modifier-practice-level-rif-perf-year-2016.xlsx"
}